oyeyipo.py
oyeyipo-0.0.1.dev1.dist-info/LICENSE
oyeyipo-0.0.1.dev1.dist-info/METADATA
oyeyipo-0.0.1.dev1.dist-info/WHEEL
oyeyipo-0.0.1.dev1.dist-info/entry_points.txt
oyeyipo-0.0.1.dev1.dist-info/top_level.txt
oyeyipo-0.0.1.dev1.dist-info/RECORD
