Metadata-Version: 2.1
Name: oyeyipo
Version: 0.0.1.dev1
Summary: About Oyeyipo Olawale as a Python package
Home-page: https://github.com/oyeyipo/oyeyipo.py
Author: Oyeyipo Olawale
Author-email: oyeyipoos@gmail.com
License: MIT
Project-URL: Tracker, https://github.com/oyeyipo/oyeyipo.py/issues
Platform: UNKNOWN
Classifier: Programming Language :: Python :: 3
Classifier: License :: OSI Approved :: MIT License
Classifier: Operating System :: OS Independent
Requires-Python: >=3.6
License-File: LICENSE
